nf_core/.pre-commit-prettier-config.yaml
nf_core/__init__.py
nf_core/__main__.py
nf_core/commands_modules.py
nf_core/commands_pipelines.py
nf_core/commands_subworkflows.py
nf_core/commands_test_datasets.py
nf_core/synced_repo.py
nf_core/utils.py
nf_core/assets/logo/MavenPro-Bold.ttf
nf_core/assets/logo/nf-core-repo-logo-base-darkbg.png
nf_core/assets/logo/nf-core-repo-logo-base-lightbg.png
nf_core/assets/logo/placeholder_logo.svg
nf_core/components/__init__.py
nf_core/components/components_command.py
nf_core/components/components_completion.py
nf_core/components/components_differ.py
nf_core/components/components_test.py
nf_core/components/components_utils.py
nf_core/components/constants.py
nf_core/components/create.py
nf_core/components/info.py
nf_core/components/install.py
nf_core/components/list.py
nf_core/components/nfcore_component.py
nf_core/components/patch.py
nf_core/components/remove.py
nf_core/components/update.py
nf_core/components/lint/__init__.py
nf_core/module-template/environment.yml
nf_core/module-template/main.nf
nf_core/module-template/meta.yml
nf_core/module-template/tests/main.nf.test.j2
nf_core/modules/__init__.py
nf_core/modules/bump_versions.py
nf_core/modules/create.py
nf_core/modules/info.py
nf_core/modules/install.py
nf_core/modules/list.py
nf_core/modules/modules_json.py
nf_core/modules/modules_repo.py
nf_core/modules/modules_utils.py
nf_core/modules/patch.py
nf_core/modules/remove.py
nf_core/modules/update.py
nf_core/modules/lint/__init__.py
nf_core/modules/lint/environment_yml.py
nf_core/modules/lint/main_nf.py
nf_core/modules/lint/meta_yml.py
nf_core/modules/lint/module_changes.py
nf_core/modules/lint/module_deprecations.py
nf_core/modules/lint/module_patch.py
nf_core/modules/lint/module_tests.py
nf_core/modules/lint/module_todos.py
nf_core/modules/lint/module_version.py
nf_core/pipeline-template/.gitattributes
nf_core/pipeline-template/.gitignore
nf_core/pipeline-template/.nf-core.yml
nf_core/pipeline-template/.pre-commit-config.yaml
nf_core-3.5.2.dist-info/licenses/LICENSE
nf_core-3.5.2.dist-info/METADATA
nf_core-3.5.2.dist-info/WHEEL
nf_core-3.5.2.dist-info/entry_points.txt
nf_core-3.5.2.dist-info/top_level.txt
nf_core-3.5.2.dist-info/RECORD
