Metadata-Version: 2.4
Name: nf-core
Version: 3.5.2
Summary: Helper tools for use with nf-core Nextflow pipelines.
Author-email: Phil Ewels <phil.ewels@scilifelab.se>
License-Expression: MIT
Project-URL: Homepage, https://github.com/nf-core/tools
Project-URL: Documentation, https://nf-co.re/docs/nf-core-tools
Project-URL: Repository, https://github.com/nf-core/tools
Project-URL: Changelog, https://github.com/nf-core/tools/blob/master/CHANGELOG.md
Keywords: nf-core,nextflow,bioinformatics,workflow,pipeline,biology,sequencing,NGS,next generation sequencing
Requires-Python: <4,>=3.10
License-File: LICENSE
Requires-Dist: click
Requires-Dist: filetype
Requires-Dist: GitPython
Requires-Dist: PyGithub
Requires-Dist: jinja2
Requires-Dist: jsonschema>=4.0
Requires-Dist: markdown>=3.3
Requires-Dist: packaging
Requires-Dist: pillow
Requires-Dist: pre-commit
Requires-Dist: prompt_toolkit<=3.0.52
Requires-Dist: pydantic>=2.2.1
Requires-Dist: pyyaml
Requires-Dist: questionary>=2.0.1
Requires-Dist: refgenie
Requires-Dist: requests
Requires-Dist: requests_cache
Requires-Dist: rich-click==1.9.*
Requires-Dist: rich>=13.3.1
Requires-Dist: rocrate
Requires-Dist: repo2rocrate
Requires-Dist: tabulate
Requires-Dist: textual==7.4.0
Requires-Dist: trogon
Requires-Dist: pdiff
Requires-Dist: ruamel.yaml
Provides-Extra: dev
Requires-Dist: mypy; extra == "dev"
Requires-Dist: myst_parser; extra == "dev"
Requires-Dist: pytest-cov; extra == "dev"
Requires-Dist: pytest-datafiles; extra == "dev"
Requires-Dist: responses; extra == "dev"
Requires-Dist: prek; extra == "dev"
Requires-Dist: ruff; extra == "dev"
Requires-Dist: Sphinx; extra == "dev"
Requires-Dist: sphinx-rtd-theme; extra == "dev"
Requires-Dist: textual-dev==1.8.0; extra == "dev"
Requires-Dist: types-PyYAML; extra == "dev"
Requires-Dist: types-requests; extra == "dev"
Requires-Dist: types-jsonschema; extra == "dev"
Requires-Dist: types-Markdown; extra == "dev"
Requires-Dist: types-setuptools; extra == "dev"
Requires-Dist: typing_extensions>=4.0.0; extra == "dev"
Requires-Dist: pytest-asyncio; extra == "dev"
Requires-Dist: pytest-textual-snapshot==1.1.0; extra == "dev"
Requires-Dist: pytest-workflow>=2.0.0; extra == "dev"
Requires-Dist: pytest-xdist>=3.7.0; extra == "dev"
Requires-Dist: pytest>=8.0.0; extra == "dev"
Dynamic: license-file
